repiet/__init__.py
repiet/__main__.py
repiet/_main.py
repiet/backends.py
repiet/compiler.py
repiet/lexer.py
repiet/optimizer.py
repiet/parser.py
repiet/test.py
repiet/tracer.py
repiet/util.py
repiet/_backends/__init__.py
repiet/_backends/c.py
repiet/_backends/cpp.py
repiet/_backends/generic.py
repiet/_backends/ir.py
repiet/_backends/piet.py
repiet/_backends/py.py
repiet-0.2.1.dist-info/LICENSE
repiet-0.2.1.dist-info/METADATA
repiet-0.2.1.dist-info/WHEEL
repiet-0.2.1.dist-info/entry_points.txt
repiet-0.2.1.dist-info/top_level.txt
repiet-0.2.1.dist-info/RECORD
