Metadata-Version: 2.1
Name: repiet
Version: 0.2.1
Summary: A Piet compiler, targeting a variety of languages (including Piet)
Home-page: https://github.com/boothby/repiet
Author: Kelly Boothby
Author-email: UNKNOWN
License: UNKNOWN
Platform: UNKNOWN
Requires-Dist: Pillow
